<?xml version="1.0" encoding="utf-8"?>
<!DOCTYPE hibernate-mapping PUBLIC "-//Hibernate/Hibernate Mapping DTD 3.0//EN"
"http://hibernate.sourceforge.net/hibernate-mapping-3.0.dtd">
<!-- 
    Mapping file autogenerated by MyEclipse Persistence Tools
-->
<hibernate-mapping>
    <class name="org.model.Order" table="order" catalog="pe_shop">
        <id name="id" type="java.lang.Integer">
            <column name="id" />
            <generator class="native" />
        </id>
        <many-to-one name="userInfo" class="org.model.UserInfo" fetch="select">
            <column name="user_id" not-null="true">
                <comment>用户ID</comment>
            </column>
        </many-to-one>
        <many-to-one name="comment" class="org.model.Comment" fetch="select">
            <column name="comment_id">
                <comment>评论ID</comment>
            </column>
        </many-to-one>
        <property name="address" type="java.lang.String">
        	<column name="address" not-null="true">
                <comment>收件地址</comment>
            </column>
        </property>
        <property name="name" type="java.lang.String">
        	<column name="name" length="25" not-null="true">
                <comment>收件人姓名</comment>
            </column>
       	</property>
        <property name="phone" type="java.lang.String">
            <column name="phone" length="20" not-null="true">
                <comment>手机号</comment>
            </column>
        </property>
        <property name="totalprices" type="java.lang.Double">
            <column name="totalprices" precision="9" not-null="true">
                <comment>总价</comment>
            </column>
        </property>
        <property name="time" type="java.sql.Timestamp">
            <column name="time" length="19" not-null="true">
                <comment>生成时间</comment>
            </column>
        </property>
        <property name="status" type="java.lang.String">
            <column name="status" length="1" not-null="true">
                <comment>状态</comment>
            </column>
        </property>
        <set name="goodsLists" inverse="true">
            <key>
                <column name="order_id">
                    <comment>订单ID</comment>
                </column>
            </key>
            <one-to-many class="org.model.GoodsList" />
        </set>
        <set name="distributes" inverse="true">
            <key>
                <column name="order_id" not-null="true">
                    <comment>订单ID</comment>
                </column>
            </key>
            <one-to-many class="org.model.Distribute" />
        </set>
        <set name="comments" inverse="true">
            <key>
                <column name="order_id">
                    <comment>订单ID</comment>
                </column>
            </key>
            <one-to-many class="org.model.Comment" />
        </set>
    </class>
</hibernate-mapping>
